datamaxi/__init__.py
datamaxi/__version__.py
datamaxi/api.py
datamaxi/error.py
datamaxi/datamaxi/__init__.py
datamaxi/datamaxi/cex.py
datamaxi/datamaxi/cex_announcement.py
datamaxi/datamaxi/cex_candle.py
datamaxi/datamaxi/cex_fee.py
datamaxi/datamaxi/cex_ticker.py
datamaxi/datamaxi/cex_token.py
datamaxi/datamaxi/cex_wallet_status.py
datamaxi/datamaxi/dex.py
datamaxi/datamaxi/forex.py
datamaxi/datamaxi/funding_rate.py
datamaxi/datamaxi/premium.py
datamaxi/datamaxi/utils.py
datamaxi/lib/constants.py
datamaxi/lib/utils.py
datamaxi/naver/__init__.py
datamaxi/telegram/__init__.py
datamaxi-0.26.3.dist-info/licenses/LICENSE
datamaxi-0.26.3.dist-info/METADATA
datamaxi-0.26.3.dist-info/WHEEL
datamaxi-0.26.3.dist-info/top_level.txt
datamaxi-0.26.3.dist-info/RECORD
