Metadata-Version: 2.4
Name: datamaxi
Version: 0.26.3
Summary: Official Python SDK for DataMaxi+ API
Author-email: Bisonai <business@bisonai.com>
Project-URL: Homepage, https://github.com/bisonai/datamaxi-python
Project-URL: Issues, https://github.com/bisonai/datamaxi-python/issues
Classifier: Intended Audience :: Developers
Classifier: Intended Audience :: Financial and Insurance Industry
Classifier: License :: OSI Approved :: MIT License
Classifier: Programming Language :: Python :: 3.10
Classifier: Programming Language :: Python :: 3.11
Classifier: Programming Language :: Python :: 3.12
Classifier: Programming Language :: Python :: 3.13
Classifier: Programming Language :: Python :: 3.14
Requires-Python: >=3.8
License-File: LICENSE
Requires-Dist: requests==2.32.5
Requires-Dist: pandas==3.0.0; python_version >= "3.11"
Requires-Dist: pandas==2.2.3; python_version < "3.11"
Dynamic: license-file
